stringencrypt/__init__.py
stringencrypt/stringencrypt.py
stringencrypt-1.0.0.dist-info/METADATA
stringencrypt-1.0.0.dist-info/WHEEL
stringencrypt-1.0.0.dist-info/top_level.txt
stringencrypt-1.0.0.dist-info/RECORD
