Metadata-Version: 2.1
Name: stringencrypt
Version: 1.0.0
Summary: StringEncrypt page allows you to encrypt strings and files using randomly generated algorithm, generating a unique decryption code (so called polymorphic code) each time in the selected programming language.
Home-page: https://www.stringencrypt.com
Author: Bartosz Wójcik
Author-email: support@pelock.com
License: Apache-2.0
Keywords: encryption string file string-encryption file-encryption security cryptography
Platform: UNKNOWN
Classifier: Development Status :: 5 - Production/Stable
Classifier: Topic :: Software Development :: Libraries :: Python Modules
Classifier: Natural Language :: English
Classifier: License :: OSI Approved :: Apache Software License
Classifier: Programming Language :: Python :: 3
